dbxconfig/__init__.py
dbxconfig/_config.py
dbxconfig/_decorators.py
dbxconfig/_logging_config.py
dbxconfig/_project.py
dbxconfig/_spark_context.py
dbxconfig/_stage_type.py
dbxconfig/_table_mapping.py
dbxconfig/_tables.py
dbxconfig/_timeslice.py
dbxconfig/_utils.py
dbxconfig/datallake.py
dbxconfig/dataset/__init__.py
dbxconfig/dataset/_dataset.py
dbxconfig/dataset/_deltalake.py
dbxconfig/dataset/_factory.py
dbxconfig/dataset/_read.py
dbxconfig/dataset/_write.py
dbxconfig/dataset/dataset_type.py
dbxconfig/workflow/__init__.py
dbxconfig/workflow/_multi_threaded.py
dbxconfig/workflow/_notebook.py
dbxconfig-5.0.7.dist-info/METADATA
dbxconfig-5.0.7.dist-info/WHEEL
dbxconfig-5.0.7.dist-info/top_level.txt
dbxconfig-5.0.7.dist-info/RECORD
