Metadata-Version: 2.1
Name: dbxconfig
Version: 5.0.7
Summary: Databricks Configuration Framework
Home-page: https://dbxconfig.readthedocs.io/en/latest/
Author: Shaun Ryan
Author-email: shaun_chiburi@hotmail.com
License: MIT
Project-URL: GitHub, https://github.com/semanticinsight/dbxconfig
Project-URL: Documentation, https://dbxconfig.readthedocs.io/en/latest/
Classifier: License :: OSI Approved :: MIT License
Classifier: Programming Language :: Python :: 3
Classifier: Programming Language :: Python :: 3.8
Requires-Dist: PyYAML
Requires-Dist: jinja2
Requires-Dist: pydantic
